setup.py
dsnd_probability_package/Binomialdistribution.py
dsnd_probability_package/Gaussiandistribution.py
dsnd_probability_package/Generaldistribution.py
dsnd_probability_package/__init__.py
dsnd_probability_package.egg-info/PKG-INFO
dsnd_probability_package.egg-info/SOURCES.txt
dsnd_probability_package.egg-info/dependency_links.txt
dsnd_probability_package.egg-info/not-zip-safe
dsnd_probability_package.egg-info/top_level.txt