Metadata-Version: 1.0
Name: dsnd-probability-package
Version: 1.0
Summary: Gaussian and Binomial distributions
Home-page: UNKNOWN
Author: Ajit patel
Author-email: ajeetpatel021@gmail.com
License: UNKNOWN
Platform: UNKNOWN
